environment_extractor/__init__.py
environment_extractor/environment_extractor.py
environment_extractor-0.1.1.data/scripts/environment_extractor.py
environment_extractor-0.1.1.dist-info/LICENSE.txt
environment_extractor-0.1.1.dist-info/METADATA
environment_extractor-0.1.1.dist-info/WHEEL
environment_extractor-0.1.1.dist-info/entry_points.txt
environment_extractor-0.1.1.dist-info/top_level.txt
environment_extractor-0.1.1.dist-info/RECORD
