Metadata-Version: 2.1
Name: environment-extractor
Version: 0.1.1
Summary: Utility to create an environment.yml file from imports.
Home-page: UNKNOWN
Author: Joshua Brooke
Author-email: joshua.brooke@outlook.com
License: UNKNOWN
Platform: UNKNOWN
Classifier: Programming Language :: Python :: 3
Classifier: License :: OSI Approved :: MIT License
Classifier: Operating System :: OS Independent
Requires-Python: >=3.0
Requires-Dist: stdlib-list
